sanic_restplus/__about__.py
sanic_restplus/__init__.py
sanic_restplus/_http.py
sanic_restplus/api.py
sanic_restplus/cors.py
sanic_restplus/errors.py
sanic_restplus/fields.py
sanic_restplus/inputs.py
sanic_restplus/marshalling.py
sanic_restplus/mask.py
sanic_restplus/model.py
sanic_restplus/namespace.py
sanic_restplus/postman.py
sanic_restplus/representations.py
sanic_restplus/reqparse.py
sanic_restplus/resource.py
sanic_restplus/restplus.py
sanic_restplus/swagger.py
sanic_restplus/utils.py
sanic_restplus/schemas/__init__.py
sanic_restplus/schemas/oas-2.0.json
sanic_restplus/static/droid-sans.css
sanic_restplus/static/favicon-16x16.png
sanic_restplus/static/favicon-32x32.png
sanic_restplus/static/swagger-ui-bundle.js
sanic_restplus/static/swagger-ui-bundle.js.map
sanic_restplus/static/swagger-ui-standalone-preset.js
sanic_restplus/static/swagger-ui-standalone-preset.js.map
sanic_restplus/static/swagger-ui.css
sanic_restplus/static/swagger-ui.css.map
sanic_restplus/static/swagger-ui.js
sanic_restplus/static/swagger-ui.js.map
sanic_restplus/static/files/.npmignore
sanic_restplus/static/files/droid-sans-latin-400.woff
sanic_restplus/static/files/droid-sans-latin-400.woff2
sanic_restplus/static/files/droid-sans-latin-700.woff
sanic_restplus/static/files/droid-sans-latin-700.woff2
sanic_restplus/templates/swagger-ui-css.html
sanic_restplus/templates/swagger-ui-libs.html
sanic_restplus/templates/swagger-ui.html
sanic_restplus-0.6.4.dist-info/AUTHORS.rst
sanic_restplus-0.6.4.dist-info/LICENSE
sanic_restplus-0.6.4.dist-info/METADATA
sanic_restplus-0.6.4.dist-info/WHEEL
sanic_restplus-0.6.4.dist-info/entry_points.txt
sanic_restplus-0.6.4.dist-info/top_level.txt
sanic_restplus-0.6.4.dist-info/RECORD
