Metadata-Version: 2.1
Name: sanic-restplus
Version: 0.6.4
Summary: Fully featured framework for fast, easy and documented API development with Sanic
Home-page: https://github.com/ashleysommer/sanic-restplus
Author: Ashley Sommer
Author-email: ashleysommer@gmail.com
License: MIT
Keywords: sanic restplus rest api swagger openapi
Platform: UNKNOWN
Classifier: Development Status :: 3 - Alpha
Classifier: Programming Language :: Python
Classifier: Environment :: Web Environment
Classifier: Operating System :: OS Independent
Classifier: Intended Audience :: Developers
Classifier: Topic :: System :: Software Distribution
Classifier: Programming Language :: Python
Classifier: Programming Language :: Python :: 3
Classifier: Programming Language :: Python :: 3 :: Only
Classifier: Programming Language :: Python :: 3.7
Classifier: Programming Language :: Python :: 3.8
Classifier: Programming Language :: Python :: 3.9
Classifier: Programming Language :: Python :: Implementation :: PyPy
Classifier: Topic :: Software Development :: Libraries :: Python Modules
Classifier: License :: OSI Approved :: MIT License
Requires-Python: >=3.7
Requires-Dist: aniso8601 (>=0.82)
Requires-Dist: jsonschema
Requires-Dist: methodtools
Requires-Dist: setuptools (>=40.8)
Requires-Dist: sanic (<22,>=21.3.4)
Requires-Dist: sanic-jinja2 (>=0.10.0)
Requires-Dist: sanic-plugin-toolkit (>=1.1.0.post1)
Provides-Extra: doc
Requires-Dist: alabaster (==0.7.12) ; extra == 'doc'
Requires-Dist: Sphinx (==2.1.2) ; extra == 'doc'
Requires-Dist: sphinx-issues (==1.2.0) ; extra == 'doc'
Provides-Extra: test
Requires-Dist: blinker ; extra == 'test'
Requires-Dist: mock (==2.0.0) ; extra == 'test'
Requires-Dist: pytest (<4.6.0) ; extra == 'test'
Requires-Dist: pytest-benchmark (==3.2.2) ; extra == 'test'
Requires-Dist: pytest-cov (==2.7.1) ; extra == 'test'
Requires-Dist: pytest-faker (==2.0.0) ; extra == 'test'
Requires-Dist: pytest-asyncio ; extra == 'test'
Requires-Dist: pytest-mock (==1.10.4) ; extra == 'test'
Requires-Dist: pytest-profiling (==1.7.0) ; extra == 'test'
Requires-Dist: pytest-sugar (==0.9.2) ; extra == 'test'
Requires-Dist: sanic-testing (>=0.4.0) ; extra == 'test'
Requires-Dist: tzlocal ; extra == 'test'
